silvaq_libs/__init__.py
silvaq_libs/dir.py
silvaq_libs/file.py
silvaq_libs/logger.py
silvaq_libs/mail.py
silvaq_libs/time.py
silvaq_lib-0.1.5.dist-info/METADATA
silvaq_lib-0.1.5.dist-info/WHEEL
silvaq_lib-0.1.5.dist-info/top_level.txt
silvaq_lib-0.1.5.dist-info/RECORD
