Metadata-Version: 2.1
Name: silvaq-lib
Version: 0.1.5
Summary: 个人常用功能封装
Home-page: https://github.com/SilvaQ/silvaq-pylib
Author: silvaq
Author-email: babbage@hotmail.com
License: UNKNOWN
Platform: UNKNOWN
Classifier: Programming Language :: Python :: 3
Classifier: License :: OSI Approved :: MIT License
Classifier: Operating System :: OS Independent
